pytorch_saver/__init__.py
pytorch_saver/_helpers.py
pytorch_saver/_model_container.py
pytorch_saver-0.1.1.dist-info/METADATA
pytorch_saver-0.1.1.dist-info/WHEEL
pytorch_saver-0.1.1.dist-info/licenses/LICENSE
pytorch_saver-0.1.1.dist-info/RECORD
