Metadata-Version: 2.1
Name: pytorch_saver
Version: 0.1.1
Summary: Simple helper to save and load PyTorch models
Author-email: Matheus Pedroni <pnmatheus@protonmail.com>
License: MIT License
License-File: LICENSE
Classifier: License :: OSI Approved :: MIT License
Classifier: Operating System :: OS Independent
Classifier: Programming Language :: Python :: 3
Requires-Python: >=3.8
Requires-Dist: torch>=1.8.2
